{
  "parks": [
    {
      "id": 1,
      "name": "Beach Park",
      "email": "Sincere@april.biz",
      "address": {
        "street": "Kulas Light",
        "suite": "Apt. 556",
        "state": "Santa Catarina",
        "city": "Gwenborough",
        "zipcode": "92998-3874",
        "geo": {
          "lat": "-3.8438855578813733",
          "lng": "-38.39056982161427"
        }
      },
      "time": {
        "openingTime": "11h",
        "closingTime": "17h"
      },
      "ticketPrice": "R$ 255,00",
      "phone": "1-770-736-8031 x56442",
      "parkWebsite": "https://www.beachpark.com.br/mobile/pt/",
      "ticketWebsite": "https://ingresso.beachpark.com.br/",
      "image": "https://img.r7.com/images/2015/12/24/1hxiwrr3ng_8mq6jr2w8y_file.jpg?dimensions=771x420&no_crop=true",
      "youtubeVideoId": "oTwB8NA17hg",
      "facebookUsername": "BeachParkBrasil",
      "instagramUsername": "beachpark",
      "twitterUsername": "beachpark"
    }
  ]
}
